oarepo_iiif/__init__.py
oarepo_iiif/ext.py
oarepo_iiif/version.py
oarepo_iiif-1.1.4.dist-info/LICENSE
oarepo_iiif-1.1.4.dist-info/METADATA
oarepo_iiif-1.1.4.dist-info/WHEEL
oarepo_iiif-1.1.4.dist-info/entry_points.txt
oarepo_iiif-1.1.4.dist-info/top_level.txt
oarepo_iiif-1.1.4.dist-info/RECORD
